exporters/__init__.py
exporters/compression.py
exporters/decompressors.py
exporters/default_retries.py
exporters/defaults.py
exporters/deserializers.py
exporters/exceptions.py
exporters/exporter_config.py
exporters/iterio.py
exporters/meta.py
exporters/module_loader.py
exporters/progress_callback.py
exporters/python_interpreter.py
exporters/utils.py
exporters/write_buffer.py
exporters/bypasses/__init__.py
exporters/bypasses/base.py
exporters/bypasses/base_s3_bypass.py
exporters/bypasses/s3_bypass_state.py
exporters/bypasses/s3_to_azure_blob_bypass.py
exporters/bypasses/s3_to_azure_file_bypass.py
exporters/bypasses/s3_to_s3_bypass.py
exporters/bypasses/stream_bypass.py
exporters/contrib/__init__.py
exporters/contrib/export_formatter/__init__.py
exporters/contrib/export_managers/__init__.py
exporters/contrib/filters/__init__.py
exporters/contrib/groupers/__init__.py
exporters/contrib/logger/__init__.py
exporters/contrib/notifications/__init__.py
exporters/contrib/persistence/__init__.py
exporters/contrib/readers/__init__.py
exporters/contrib/stats_managers/__init__.py
exporters/contrib/transform/__init__.py
exporters/contrib/writers/__init__.py
exporters/contrib/writers/odo_writer.py
exporters/export_formatter/__init__.py
exporters/export_formatter/base_export_formatter.py
exporters/export_formatter/csv_export_formatter.py
exporters/export_formatter/json_export_formatter.py
exporters/export_formatter/xml_export_formatter.py
exporters/export_managers/__init__.py
exporters/export_managers/base_exporter.py
exporters/export_managers/basic_exporter.py
exporters/filters/__init__.py
exporters/filters/base_filter.py
exporters/filters/dupe_filter.py
exporters/filters/key_value_filter.py
exporters/filters/key_value_filters.py
exporters/filters/key_value_regex_filter.py
exporters/filters/no_filter.py
exporters/filters/pythonexp_filter.py
exporters/groupers/__init__.py
exporters/groupers/base_grouper.py
exporters-0.7.0.dist-info/top_level.txt
exporters-0.7.0.dist-info/dependency_links.txt
exporters-0.7.0.dist-info/METADATA
exporters-0.7.0.dist-info/DESCRIPTION.rst
exporters-0.7.0.dist-info/metadata.json
exporters-0.7.0.dist-info/WHEEL
exporters-0.7.0.dist-info/RECORD
