Metadata-Version: 2.0
Name: exporters
Version: 0.7.0
Summary: Exporters is an extensible export pipeline library that supports filter, transform and several sources and destinations.
Home-page: https://github.com/scrapinghub/exporters
Author: Scrapinghub
Author-email: info@scrapinghub
License: BSD
Keywords: exporters export data
Platform: UNKNOWN
Classifier: Development Status :: 4 - Beta
Classifier: Intended Audience :: Developers
Classifier: Natural Language :: English
Classifier: License :: OSI Approved :: BSD License
Classifier: Programming Language :: Python :: 2.7
Requires-Dist: six
Requires-Dist: retrying
Requires-Dist: requests
Requires-Dist: PyYAML
Requires-Dist: decorator
Provides-Extra: azure
Requires-Dist: azure; extra == 'azure'
Provides-Extra: bz2
Requires-Dist: bz2file; extra == 'bz2'
Provides-Extra: csv
Requires-Dist: boltons; extra == 'csv'
Provides-Extra: gcloud
Requires-Dist: gcloud; extra == 'gcloud'
Provides-Extra: gdrive
Requires-Dist: PyDrive; extra == 'gdrive'
Provides-Extra: hubstorage
Requires-Dist: hubstorage; extra == 'hubstorage'
Requires-Dist: collection-scanner; extra == 'hubstorage'
Provides-Extra: jq
Requires-Dist: jq; extra == 'jq'
Provides-Extra: kafka
Requires-Dist: kafka-python; extra == 'kafka'
Requires-Dist: msgpack-python; extra == 'kafka'
Requires-Dist: kafka-scanner; extra == 'kafka'
Provides-Extra: mysql
Requires-Dist: mysql-python; extra == 'mysql'
Requires-Dist: SQLAlchemy; extra == 'mysql'
Provides-Extra: notifications
Requires-Dist: Jinja2; extra == 'notifications'
Provides-Extra: odo
Requires-Dist: flatson; extra == 'odo'
Requires-Dist: odo; extra == 'odo'
Requires-Dist: pandas; extra == 'odo'
Provides-Extra: postgres
Requires-Dist: psycopg2; extra == 'postgres'
Requires-Dist: SQLAlchemy; extra == 'postgres'
Provides-Extra: s3
Requires-Dist: boto; extra == 's3'
Requires-Dist: dateparser; extra == 's3'
Provides-Extra: sftp
Requires-Dist: pysftp; extra == 'sftp'
Requires-Dist: ecdsa; extra == 'sftp'
Requires-Dist: paramiko; extra == 'sftp'
Requires-Dist: pycryptowsgiref; extra == 'sftp'
Provides-Extra: sqlite
Requires-Dist: sqlitedict; extra == 'sqlite'
Requires-Dist: SQLAlchemy; extra == 'sqlite'
Provides-Extra: xml
Requires-Dist: dicttoxml; extra == 'xml'
